{
  "annotations": {
    "list": [
      {
        "builtIn": 1,
        "datasource": "-- Grafana --",
        "enable": true,
        "hide": true,
        "iconColor": "rgba(0, 211, 255, 1)",
        "name": "Annotations & Alerts",
        "type": "dashboard"
      }
    ]
  },
  "editable": true,
  "gnetId": null,
  "graphTooltip": 0,
  "links": [],
  "panels": [
    {
      "datasource": "${datasource}",
      "fieldConfig": {
        "defaults": {
          "color": {
            "mode": "thresholds"
          },
          "mappings": [],
          "thresholds": {
            "mode": "absolute",
            "steps": [
              {
                "color": "green",
                "value": null
              },
              {
                "color": "red",
                "value": 80
              }
            ]
          }
        },
        "overrides": []
      },
      "gridPos": {
        "h": 8,
        "w": 6,
        "x": 0,
        "y": 0
      },
      "id": 2,
      "options": {
        "colorMode": "value",
        "graphMode": "area",
        "justifyMode": "auto",
        "orientation": "auto",
        "reduceOptions": {
          "calcs": [
            "lastNotNull"
          ],
          "fields": "",
          "values": false
        },
        "text": {},
        "textMode": "auto"
      },
      "pluginVersion": "8.0.4",
      "targets": [
        {
          "queryType": "randomWalk",
          "refId": "A",
          "target": "jobmanager.jobmanager.numRegisteredTaskManagers"
        }
      ],
      "title": "n째 task managers",
      "type": "stat"
    },
    {
      "datasource": "${datasource}",
      "fieldConfig": {
        "defaults": {
          "color": {
            "mode": "thresholds"
          },
          "mappings": [],
          "thresholds": {
            "mode": "absolute",
            "steps": [
              {
                "color": "green",
                "value": null
              },
              {
                "color": "red",
                "value": 80
              }
            ]
          }
        },
        "overrides": []
      },
      "gridPos": {
        "h": 8,
        "w": 6,
        "x": 6,
        "y": 0
      },
      "id": 3,
      "options": {
        "colorMode": "value",
        "graphMode": "area",
        "justifyMode": "auto",
        "orientation": "auto",
        "reduceOptions": {
          "calcs": [
            "lastNotNull"
          ],
          "fields": "",
          "values": false
        },
        "text": {},
        "textMode": "auto"
      },
      "pluginVersion": "8.0.4",
      "targets": [
        {
          "queryType": "randomWalk",
          "refId": "A",
          "target": "jobmanager.jobmanager.taskSlotsAvailable"
        }
      ],
      "title": "n째 task slots available",
      "type": "stat"
    },
    {
      "datasource": "${datasource}",
      "fieldConfig": {
        "defaults": {
          "color": {
            "mode": "thresholds"
          },
          "mappings": [],
          "thresholds": {
            "mode": "absolute",
            "steps": [
              {
                "color": "green",
                "value": null
              },
              {
                "color": "red",
                "value": 80
              }
            ]
          }
        },
        "overrides": []
      },
      "gridPos": {
        "h": 8,
        "w": 6,
        "x": 12,
        "y": 0
      },
      "id": 4,
      "options": {
        "colorMode": "value",
        "graphMode": "area",
        "justifyMode": "auto",
        "orientation": "auto",
        "reduceOptions": {
          "calcs": [
            "lastNotNull"
          ],
          "fields": "",
          "values": false
        },
        "text": {},
        "textMode": "auto"
      },
      "pluginVersion": "8.0.4",
      "targets": [
        {
          "queryType": "randomWalk",
          "refId": "A",
          "target": "jobmanager.jobmanager.numRunningJobs"
        }
      ],
      "title": "n째 running jobs",
      "type": "stat"
    },
    {
      "datasource": "${datasource}",
      "fieldConfig": {
        "defaults": {
          "color": {
            "mode": "thresholds"
          },
          "mappings": [],
          "thresholds": {
            "mode": "absolute",
            "steps": [
              {
                "color": "green",
                "value": null
              },
              {
                "color": "red",
                "value": 80
              }
            ]
          }
        },
        "overrides": []
      },
      "gridPos": {
        "h": 8,
        "w": 6,
        "x": 18,
        "y": 0
      },
      "id": 5,
      "options": {
        "colorMode": "value",
        "graphMode": "area",
        "justifyMode": "auto",
        "orientation": "auto",
        "reduceOptions": {
          "calcs": [
            "lastNotNull"
          ],
          "fields": "",
          "values": false
        },
        "text": {},
        "textMode": "auto"
      },
      "pluginVersion": "8.0.4",
      "targets": [
        {
          "queryType": "randomWalk",
          "refId": "A",
          "target": "jobmanager.jobmanager.taskSlotsTotal"
        }
      ],
      "title": "n째 task slots total",
      "type": "stat"
    },
    {
      "collapsed": false,
      "datasource": null,
      "gridPos": {
        "h": 1,
        "w": 24,
        "x": 0,
        "y": 8
      },
      "id": 29,
      "panels": [],
      "title": "CPU",
      "type": "row"
    },
    {
      "datasource": "${datasource}",
      "fieldConfig": {
        "defaults": {
          "color": {
            "mode": "palette-classic"
          },
          "custom": {
            "axisLabel": "",
            "axisPlacement": "auto",
            "barAlignment": 0,
            "drawStyle": "line",
            "fillOpacity": 0,
            "gradientMode": "none",
            "hideFrom": {
              "legend": false,
              "tooltip": false,
              "viz": false
            },
            "lineInterpolation": "linear",
            "lineWidth": 1,
            "pointSize": 5,
            "scaleDistribution": {
              "type": "linear"
            },
            "showPoints": "auto",
            "spanNulls": false,
            "stacking": {
              "group": "A",
              "mode": "none"
            },
            "thresholdsStyle": {
              "mode": "off"
            }
          },
          "mappings": [],
          "thresholds": {
            "mode": "absolute",
            "steps": [
              {
                "color": "green",
                "value": null
              },
              {
                "color": "red",
                "value": 80
              }
            ]
          }
        },
        "overrides": []
      },
      "gridPos": {
        "h": 8,
        "w": 24,
        "x": 0,
        "y": 9
      },
      "id": 7,
      "options": {
        "legend": {
          "calcs": [],
          "displayMode": "list",
          "placement": "bottom"
        },
        "tooltip": {
          "mode": "single"
        }
      },
      "targets": [
        {
          "queryType": "randomWalk",
          "refCount": 0,
          "refId": "A",
          "target": "jobmanager.jobmanager.Status.JVM.CPU.Load"
        },
        {
          "hide": false,
          "refCount": 0,
          "refId": "B",
          "target": "jobmanager.jobmanager.Status.JVM.CPU.Time"
        }
      ],
      "title": "CPU",
      "type": "timeseries"
    },
    {
      "collapsed": false,
      "datasource": null,
      "gridPos": {
        "h": 1,
        "w": 24,
        "x": 0,
        "y": 17
      },
      "id": 24,
      "panels": [],
      "title": "Garbage collector",
      "type": "row"
    },
    {
      "datasource": "${datasource}",
      "fieldConfig": {
        "defaults": {
          "color": {
            "mode": "palette-classic"
          },
          "custom": {
            "axisLabel": "",
            "axisPlacement": "auto",
            "barAlignment": 0,
            "drawStyle": "line",
            "fillOpacity": 0,
            "gradientMode": "none",
            "hideFrom": {
              "legend": false,
              "tooltip": false,
              "viz": false
            },
            "lineInterpolation": "linear",
            "lineWidth": 1,
            "pointSize": 5,
            "scaleDistribution": {
              "type": "linear"
            },
            "showPoints": "auto",
            "spanNulls": false,
            "stacking": {
              "group": "A",
              "mode": "none"
            },
            "thresholdsStyle": {
              "mode": "off"
            }
          },
          "mappings": [],
          "thresholds": {
            "mode": "absolute",
            "steps": [
              {
                "color": "green",
                "value": null
              },
              {
                "color": "red",
                "value": 80
              }
            ]
          }
        },
        "overrides": []
      },
      "gridPos": {
        "h": 8,
        "w": 12,
        "x": 0,
        "y": 18
      },
      "id": 11,
      "options": {
        "legend": {
          "calcs": [],
          "displayMode": "list",
          "placement": "bottom"
        },
        "tooltip": {
          "mode": "single"
        }
      },
      "targets": [
        {
          "queryType": "randomWalk",
          "refCount": 0,
          "refId": "A",
          "target": "jobmanager.jobmanager.Status.JVM.GarbageCollector.PS-MarkSweep.Count"
        },
        {
          "hide": false,
          "refCount": 0,
          "refId": "B",
          "target": "jobmanager.jobmanager.Status.JVM.GarbageCollector.PS-Scavenge.Count"
        }
      ],
      "title": "Garbage collector count",
      "type": "timeseries"
    },
    {
      "datasource": "${datasource}",
      "fieldConfig": {
        "defaults": {
          "color": {
            "mode": "palette-classic"
          },
          "custom": {
            "axisLabel": "",
            "axisPlacement": "auto",
            "barAlignment": 0,
            "drawStyle": "line",
            "fillOpacity": 0,
            "gradientMode": "none",
            "hideFrom": {
              "legend": false,
              "tooltip": false,
              "viz": false
            },
            "lineInterpolation": "linear",
            "lineWidth": 1,
            "pointSize": 5,
            "scaleDistribution": {
              "type": "linear"
            },
            "showPoints": "auto",
            "spanNulls": false,
            "stacking": {
              "group": "A",
              "mode": "none"
            },
            "thresholdsStyle": {
              "mode": "off"
            }
          },
          "mappings": [],
          "thresholds": {
            "mode": "absolute",
            "steps": [
              {
                "color": "green",
                "value": null
              },
              {
                "color": "red",
                "value": 80
              }
            ]
          }
        },
        "overrides": []
      },
      "gridPos": {
        "h": 8,
        "w": 12,
        "x": 12,
        "y": 18
      },
      "id": 12,
      "options": {
        "legend": {
          "calcs": [],
          "displayMode": "list",
          "placement": "bottom"
        },
        "tooltip": {
          "mode": "single"
        }
      },
      "targets": [
        {
          "queryType": "randomWalk",
          "refCount": 0,
          "refId": "A",
          "target": "jobmanager.jobmanager.Status.JVM.GarbageCollector.PS-MarkSweep.Time"
        },
        {
          "hide": false,
          "refCount": 0,
          "refId": "B",
          "target": "jobmanager.jobmanager.Status.JVM.GarbageCollector.PS-Scavenge.Time"
        }
      ],
      "title": "Garbage collector time",
      "type": "timeseries"
    },
    {
      "collapsed": false,
      "datasource": null,
      "gridPos": {
        "h": 1,
        "w": 24,
        "x": 0,
        "y": 26
      },
      "id": 22,
      "panels": [],
      "title": "Class Loader",
      "type": "row"
    },
    {
      "datasource": "${datasource}",
      "description": "",
      "fieldConfig": {
        "defaults": {
          "color": {
            "mode": "palette-classic"
          },
          "custom": {
            "axisLabel": "",
            "axisPlacement": "auto",
            "barAlignment": 0,
            "drawStyle": "line",
            "fillOpacity": 0,
            "gradientMode": "none",
            "hideFrom": {
              "legend": false,
              "tooltip": false,
              "viz": false
            },
            "lineInterpolation": "linear",
            "lineWidth": 1,
            "pointSize": 5,
            "scaleDistribution": {
              "type": "linear"
            },
            "showPoints": "auto",
            "spanNulls": false,
            "stacking": {
              "group": "A",
              "mode": "none"
            },
            "thresholdsStyle": {
              "mode": "off"
            }
          },
          "mappings": [],
          "thresholds": {
            "mode": "absolute",
            "steps": [
              {
                "color": "green",
                "value": null
              },
              {
                "color": "red",
                "value": 80
              }
            ]
          }
        },
        "overrides": []
      },
      "gridPos": {
        "h": 8,
        "w": 24,
        "x": 0,
        "y": 27
      },
      "id": 9,
      "options": {
        "legend": {
          "calcs": [],
          "displayMode": "list",
          "placement": "bottom"
        },
        "tooltip": {
          "mode": "single"
        }
      },
      "targets": [
        {
          "queryType": "randomWalk",
          "refCount": 0,
          "refId": "A",
          "target": "jobmanager.jobmanager.Status.JVM.ClassLoader.ClassesLoaded"
        },
        {
          "hide": false,
          "refCount": 0,
          "refId": "B",
          "target": "jobmanager.jobmanager.Status.JVM.ClassLoader.ClassesUnloaded"
        }
      ],
      "title": "Class Loader",
      "type": "timeseries"
    },
    {
      "collapsed": false,
      "datasource": null,
      "gridPos": {
        "h": 1,
        "w": 24,
        "x": 0,
        "y": 35
      },
      "id": 20,
      "panels": [],
      "title": "Threads",
      "type": "row"
    },
    {
      "datasource": "${datasource}",
      "fieldConfig": {
        "defaults": {
          "color": {
            "mode": "palette-classic"
          },
          "custom": {
            "axisLabel": "",
            "axisPlacement": "auto",
            "barAlignment": 0,
            "drawStyle": "line",
            "fillOpacity": 0,
            "gradientMode": "none",
            "hideFrom": {
              "legend": false,
              "tooltip": false,
              "viz": false
            },
            "lineInterpolation": "linear",
            "lineWidth": 1,
            "pointSize": 5,
            "scaleDistribution": {
              "type": "linear"
            },
            "showPoints": "auto",
            "spanNulls": false,
            "stacking": {
              "group": "A",
              "mode": "none"
            },
            "thresholdsStyle": {
              "mode": "off"
            }
          },
          "mappings": [],
          "thresholds": {
            "mode": "absolute",
            "steps": [
              {
                "color": "green",
                "value": null
              },
              {
                "color": "red",
                "value": 80
              }
            ]
          }
        },
        "overrides": []
      },
      "gridPos": {
        "h": 8,
        "w": 24,
        "x": 0,
        "y": 36
      },
      "id": 27,
      "options": {
        "legend": {
          "calcs": [],
          "displayMode": "list",
          "placement": "bottom"
        },
        "tooltip": {
          "mode": "single"
        }
      },
      "targets": [
        {
          "queryType": "randomWalk",
          "refId": "A",
          "target": "jobmanager.jobmanager.Status.JVM.Threads.Count"
        }
      ],
      "title": "Threads count",
      "type": "timeseries"
    },
    {
      "collapsed": false,
      "datasource": null,
      "gridPos": {
        "h": 1,
        "w": 24,
        "x": 0,
        "y": 44
      },
      "id": 18,
      "panels": [],
      "title": "Memory",
      "type": "row"
    },
    {
      "datasource": "${datasource}",
      "fieldConfig": {
        "defaults": {
          "color": {
            "mode": "palette-classic"
          },
          "custom": {
            "axisLabel": "",
            "axisPlacement": "auto",
            "barAlignment": 0,
            "drawStyle": "line",
            "fillOpacity": 0,
            "gradientMode": "none",
            "hideFrom": {
              "legend": false,
              "tooltip": false,
              "viz": false
            },
            "lineInterpolation": "linear",
            "lineWidth": 1,
            "pointSize": 6,
            "scaleDistribution": {
              "type": "linear"
            },
            "showPoints": "auto",
            "spanNulls": false,
            "stacking": {
              "group": "A",
              "mode": "none"
            },
            "thresholdsStyle": {
              "mode": "off"
            }
          },
          "mappings": [],
          "thresholds": {
            "mode": "absolute",
            "steps": [
              {
                "color": "green",
                "value": null
              },
              {
                "color": "red",
                "value": 80
              }
            ]
          }
        },
        "overrides": []
      },
      "gridPos": {
        "h": 7,
        "w": 6,
        "x": 0,
        "y": 45
      },
      "id": 13,
      "options": {
        "legend": {
          "calcs": [],
          "displayMode": "list",
          "placement": "bottom"
        },
        "tooltip": {
          "mode": "single"
        }
      },
      "targets": [
        {
          "queryType": "randomWalk",
          "refCount": 0,
          "refId": "A",
          "target": "jobmanager.jobmanager.Status.JVM.Memory.Direct.Count"
        },
        {
          "hide": false,
          "refCount": 0,
          "refId": "B",
          "target": "jobmanager.jobmanager.Status.JVM.Memory.Direct.MemoryUsed"
        },
        {
          "hide": false,
          "refCount": 0,
          "refId": "C",
          "target": "jobmanager.jobmanager.Status.JVM.Memory.Direct.TotalCapacity"
        }
      ],
      "title": "Direct memory",
      "type": "timeseries"
    },
    {
      "datasource": "${datasource}",
      "fieldConfig": {
        "defaults": {
          "color": {
            "mode": "palette-classic"
          },
          "custom": {
            "axisLabel": "",
            "axisPlacement": "auto",
            "barAlignment": 0,
            "drawStyle": "line",
            "fillOpacity": 0,
            "gradientMode": "none",
            "hideFrom": {
              "legend": false,
              "tooltip": false,
              "viz": false
            },
            "lineInterpolation": "linear",
            "lineWidth": 1,
            "pointSize": 5,
            "scaleDistribution": {
              "type": "linear"
            },
            "showPoints": "auto",
            "spanNulls": false,
            "stacking": {
              "group": "A",
              "mode": "none"
            },
            "thresholdsStyle": {
              "mode": "off"
            }
          },
          "mappings": [],
          "thresholds": {
            "mode": "absolute",
            "steps": [
              {
                "color": "green",
                "value": null
              },
              {
                "color": "red",
                "value": 80
              }
            ]
          }
        },
        "overrides": []
      },
      "gridPos": {
        "h": 7,
        "w": 6,
        "x": 6,
        "y": 45
      },
      "id": 14,
      "options": {
        "legend": {
          "calcs": [],
          "displayMode": "list",
          "placement": "bottom"
        },
        "tooltip": {
          "mode": "single"
        }
      },
      "targets": [
        {
          "queryType": "randomWalk",
          "refCount": 0,
          "refId": "A",
          "target": "jobmanager.jobmanager.Status.JVM.Memory.Heap.Committed"
        },
        {
          "hide": false,
          "refCount": 0,
          "refId": "B",
          "target": "jobmanager.jobmanager.Status.JVM.Memory.Heap.Max"
        },
        {
          "hide": false,
          "refCount": 0,
          "refId": "C",
          "target": "jobmanager.jobmanager.Status.JVM.Memory.Heap.Used"
        }
      ],
      "title": "Heap memory",
      "type": "timeseries"
    },
    {
      "datasource": "${datasource}",
      "fieldConfig": {
        "defaults": {
          "color": {
            "mode": "palette-classic"
          },
          "custom": {
            "axisLabel": "",
            "axisPlacement": "auto",
            "barAlignment": 0,
            "drawStyle": "line",
            "fillOpacity": 0,
            "gradientMode": "none",
            "hideFrom": {
              "legend": false,
              "tooltip": false,
              "viz": false
            },
            "lineInterpolation": "linear",
            "lineWidth": 1,
            "pointSize": 5,
            "scaleDistribution": {
              "type": "linear"
            },
            "showPoints": "auto",
            "spanNulls": false,
            "stacking": {
              "group": "A",
              "mode": "none"
            },
            "thresholdsStyle": {
              "mode": "off"
            }
          },
          "mappings": [],
          "thresholds": {
            "mode": "absolute",
            "steps": [
              {
                "color": "green",
                "value": null
              },
              {
                "color": "red",
                "value": 80
              }
            ]
          }
        },
        "overrides": []
      },
      "gridPos": {
        "h": 7,
        "w": 6,
        "x": 12,
        "y": 45
      },
      "id": 15,
      "options": {
        "legend": {
          "calcs": [],
          "displayMode": "list",
          "placement": "bottom"
        },
        "tooltip": {
          "mode": "single"
        }
      },
      "targets": [
        {
          "queryType": "randomWalk",
          "refCount": 0,
          "refId": "A",
          "target": "jobmanager.jobmanager.Status.JVM.Memory.Mapped.Count"
        },
        {
          "hide": false,
          "refCount": 0,
          "refId": "B",
          "target": "jobmanager.jobmanager.Status.JVM.Memory.Mapped.MemoryUsed"
        },
        {
          "hide": false,
          "refCount": 0,
          "refId": "C",
          "target": "jobmanager.jobmanager.Status.JVM.Memory.Mapped.TotalCapacity"
        }
      ],
      "title": "Mapped memory",
      "type": "timeseries"
    },
    {
      "datasource": "${datasource}",
      "fieldConfig": {
        "defaults": {
          "color": {
            "mode": "palette-classic"
          },
          "custom": {
            "axisLabel": "",
            "axisPlacement": "auto",
            "barAlignment": 0,
            "drawStyle": "line",
            "fillOpacity": 0,
            "gradientMode": "none",
            "hideFrom": {
              "legend": false,
              "tooltip": false,
              "viz": false
            },
            "lineInterpolation": "linear",
            "lineWidth": 1,
            "pointSize": 5,
            "scaleDistribution": {
              "type": "linear"
            },
            "showPoints": "auto",
            "spanNulls": false,
            "stacking": {
              "group": "A",
              "mode": "none"
            },
            "thresholdsStyle": {
              "mode": "off"
            }
          },
          "mappings": [],
          "thresholds": {
            "mode": "absolute",
            "steps": [
              {
                "color": "green",
                "value": null
              },
              {
                "color": "red",
                "value": 80
              }
            ]
          }
        },
        "overrides": []
      },
      "gridPos": {
        "h": 7,
        "w": 6,
        "x": 18,
        "y": 45
      },
      "id": 16,
      "options": {
        "legend": {
          "calcs": [],
          "displayMode": "list",
          "placement": "bottom"
        },
        "tooltip": {
          "mode": "single"
        }
      },
      "targets": [
        {
          "queryType": "randomWalk",
          "refCount": 0,
          "refId": "A",
          "target": "jobmanager.jobmanager.Status.JVM.Memory.Metaspace.Committed"
        },
        {
          "hide": false,
          "refCount": 0,
          "refId": "B",
          "target": "jobmanager.jobmanager.Status.JVM.Memory.Metaspace.Max"
        },
        {
          "hide": false,
          "refCount": 0,
          "refId": "C",
          "target": "jobmanager.jobmanager.Status.JVM.Memory.Metaspace.Used"
        }
      ],
      "title": "Metaspace memory",
      "type": "timeseries"
    },
    {
      "datasource": "${datasource}",
      "fieldConfig": {
        "defaults": {
          "color": {
            "mode": "palette-classic"
          },
          "custom": {
            "axisLabel": "",
            "axisPlacement": "auto",
            "barAlignment": 0,
            "drawStyle": "line",
            "fillOpacity": 0,
            "gradientMode": "none",
            "hideFrom": {
              "legend": false,
              "tooltip": false,
              "viz": false
            },
            "lineInterpolation": "linear",
            "lineWidth": 1,
            "pointSize": 5,
            "scaleDistribution": {
              "type": "linear"
            },
            "showPoints": "auto",
            "spanNulls": false,
            "stacking": {
              "group": "A",
              "mode": "none"
            },
            "thresholdsStyle": {
              "mode": "off"
            }
          },
          "mappings": [],
          "thresholds": {
            "mode": "absolute",
            "steps": [
              {
                "color": "green",
                "value": null
              },
              {
                "color": "red",
                "value": 80
              }
            ]
          }
        },
        "overrides": []
      },
      "gridPos": {
        "h": 7,
        "w": 6,
        "x": 0,
        "y": 52
      },
      "id": 25,
      "options": {
        "legend": {
          "calcs": [],
          "displayMode": "list",
          "placement": "bottom"
        },
        "tooltip": {
          "mode": "single"
        }
      },
      "targets": [
        {
          "queryType": "randomWalk",
          "refCount": 0,
          "refId": "A",
          "target": "jobmanager.jobmanager.Status.JVM.Memory.NonHeap.Committed"
        },
        {
          "hide": false,
          "refCount": 0,
          "refId": "B",
          "target": "jobmanager.jobmanager.Status.JVM.Memory.NonHeap.Max"
        },
        {
          "hide": false,
          "refCount": 0,
          "refId": "C",
          "target": "jobmanager.jobmanager.Status.JVM.Memory.NonHeap.Used"
        }
      ],
      "title": "NonHeap memory",
      "type": "timeseries"
    }
  ],
  "schemaVersion": 30,
  "style": "dark",
  "tags": [],
  "templating": {
    "list": [
      {
        "current": {
          "selected": false,
          "text": "Graphite",
          "value": "Graphite"
        },
        "description": null,
        "error": null,
        "hide": 0,
        "includeAll": false,
        "label": "datasource",
        "multi": false,
        "name": "datasource",
        "options": [],
        "query": "graphite",
        "queryValue": "",
        "refresh": 1,
        "regex": "",
        "skipUrlSync": false,
        "type": "datasource"
      }
    ]
  },
  "time": {
    "from": "now-6h",
    "to": "now"
  },
  "timepicker": {},
  "timezone": "",
  "title": "SABD_2 metrics",
  "uid": "55XzvZmnz",
  "version": 2
}